limmbo/__init__.py
limmbo/testit.py
limmbo/bin/__init__.py
limmbo/bin/runAssociation.py
limmbo/bin/runVarianceEstimation.py
limmbo/core/__init__.py
limmbo/core/gwas.py
limmbo/core/vdbootstrap.py
limmbo/core/vdsimple.py
limmbo/io/__init__.py
limmbo/io/input.py
limmbo/io/parser.py
limmbo/io/reader.py
limmbo/io/utils.py
limmbo/io/test/data/Cg.csv
limmbo/io/test/data/Cn.csv
limmbo/io/test/data/covs.csv
limmbo/io/test/data/genotypes.csv
limmbo/io/test/data/pcs.csv
limmbo/io/test/data/pheno.csv
limmbo/io/test/data/relatedness.csv
limmbo/plot/__init__.py
limmbo/plot/manhattan.py
limmbo/utils/__init__.py
limmbo/utils/utils.py
limmbo-0.1.5.dist-info/LICENSE
limmbo-0.1.5.dist-info/METADATA
limmbo-0.1.5.dist-info/WHEEL
limmbo-0.1.5.dist-info/entry_points.txt
limmbo-0.1.5.dist-info/top_level.txt
limmbo-0.1.5.dist-info/zip-safe
limmbo-0.1.5.dist-info/RECORD
