Metadata-Version: 2.1
Name: limmbo
Version: 0.1.5
Summary: Linear mixed model bootstrapping
Home-page: https://github.com/HannahVMeyer/limmbo
Author: Hannah Meyer
Author-email: hmeyer@cshl.edu
Maintainer: Hannah Meyer
Maintainer-email: hmeyer@cshl.edu
License: Apache License 2.0
Download-URL: https://github.com/HannahVMeyer/limmbo
Keywords: lmm,bootstrapping
Platform: Windows
Platform: MacOS
Platform: POSIX
Platform: POSIX :: Linux
Classifier: Development Status :: 4 - Beta
Classifier: Environment :: Console
Classifier: License :: OSI Approved :: Apache Software License
Classifier: Operating System :: OS Independent
Classifier: Programming Language :: Python
Requires-Dist: numpy (>=1.14.5)
Requires-Dist: scipy (>=1.0.0)
Requires-Dist: matplotlib
Requires-Dist: Cython (>=0.28.3)
Requires-Dist: multiprocess
Requires-Dist: pathos
Requires-Dist: bottleneck (>=1.2.1)
Requires-Dist: scipy-sugar (>=1.0.4)
Requires-Dist: limix (==1.0.18)
Requires-Dist: limix-legacy (==0.8.12)
